LICENSE.txt
README.md
setup.cfg
setup.py
units_pani/__init__.py
units_pani/units_pani.py
units_pani.egg-info/PKG-INFO
units_pani.egg-info/SOURCES.txt
units_pani.egg-info/dependency_links.txt
units_pani.egg-info/requires.txt
units_pani.egg-info/top_level.txt